django_nis2_shield/__init__.py
django_nis2_shield/cef_formatter.py
django_nis2_shield/enforcer.py
django_nis2_shield/loggers.py
django_nis2_shield/middleware.py
django_nis2_shield/siem_presets.py
django_nis2_shield/utils.py
django_nis2_shield/webhooks.py
django_nis2_shield/management/commands/check_nis2.py
django_nis2_shield/management/commands/generate_incident_report.py
django_nis2_shield/management/commands/update_threat_list.py
django_nis2_shield-1.1.1.dist-info/licenses/LICENSE
django_nis2_shield-1.1.1.dist-info/METADATA
django_nis2_shield-1.1.1.dist-info/WHEEL
django_nis2_shield-1.1.1.dist-info/top_level.txt
django_nis2_shield-1.1.1.dist-info/RECORD
