Metadata-Version: 2.4
Name: django-nis2-shield
Version: 1.1.1
Summary: A Security-First Middleware for Django to ensure NIS2 compliance with forensic logging, active defense, and SIEM integration.
Author-email: Fabrizio Di Priamo <fabrizio.di.priamo@gmail.com>
License: MIT
Project-URL: Homepage, https://github.com/nis2shield/django-nis2-shield
Project-URL: Documentation, https://github.com/nis2shield/django-nis2-shield#readme
Project-URL: Repository, https://github.com/nis2shield/django-nis2-shield.git
Project-URL: Changelog, https://github.com/nis2shield/django-nis2-shield/blob/main/CHANGELOG.md
Project-URL: Bug Tracker, https://github.com/nis2shield/django-nis2-shield/issues
Keywords: django,security,nis2,compliance,logging,siem,middleware,gdpr,audit,forensic,cybersecurity,enterprise,rate-limiting,session-guard
Classifier: Development Status :: 4 - Beta
Classifier: Framework :: Django
Classifier: Framework :: Django :: 3.2
Classifier: Framework :: Django :: 4.0
Classifier: Framework :: Django :: 4.1
Classifier: Framework :: Django :: 4.2
Classifier: Framework :: Django :: 5.0
Classifier: Intended Audience :: Developers
Classifier: License :: OSI Approved :: MIT License
Classifier: Operating System :: OS Independent
Classifier: Programming Language :: Python :: 3
Classifier: Programming Language :: Python :: 3.8
Classifier: Programming Language :: Python :: 3.9
Classifier: Programming Language :: Python :: 3.10
Classifier: Programming Language :: Python :: 3.11
Classifier: Programming Language :: Python :: 3.12
Classifier: Topic :: Security
Classifier: Topic :: System :: Logging
Classifier: Topic :: Internet :: WWW/HTTP :: WSGI :: Middleware
Requires-Python: >=3.8
License-File: LICENSE
Requires-Dist: Django>=3.2
Requires-Dist: cryptography>=41.0.0
Provides-Extra: dev
Requires-Dist: pytest>=7.0; extra == "dev"
Requires-Dist: pytest-django>=4.5; extra == "dev"
Requires-Dist: pytest-cov>=4.0; extra == "dev"
Requires-Dist: black>=23.0; extra == "dev"
Requires-Dist: isort>=5.12; extra == "dev"
Requires-Dist: flake8>=6.0; extra == "dev"
Dynamic: license-file
